libspatialize.cpython-313-darwin.so
spatialize/__init__.py
spatialize/_math_util.py
spatialize/_util.py
spatialize/_version.py
spatialize/data.py
spatialize/logging.py
spatialize/gs/__init__.py
spatialize/gs/idw.py
spatialize/gs/esi/__init__.py
spatialize/gs/esi/_main.py
spatialize/gs/esi/aggfunction.py
spatialize/gs/esi/lossfunction.py
spatialize/resources/__init__.py
spatialize/resources/data/__init__.py
spatialize/resources/data/dc1_input_data.csv
spatialize/resources/data/dc1_ok_kriging_example.csv
spatialize/resources/data/dc1_output_grid.dat
spatialize/resources/data/dc1_vario_cu_omni.csv
spatialize/resources/data/dc2_input_muestras.dat
spatialize/resources/data/dc2_output_box.csv
spatialize/resources/data/esi_idw_model.json
spatialize-1.0.2.dist-info/licenses/LICENSE
spatialize-1.0.2.dist-info/METADATA
spatialize-1.0.2.dist-info/WHEEL
spatialize-1.0.2.dist-info/top_level.txt
spatialize-1.0.2.dist-info/RECORD
