Metadata-Version: 2.4
Name: spatialize
Version: 1.0.2
Summary: Spatialize: A Python wrapper for C++ ESI library
Home-page: http://www.alges.cl/
Author: ALGES Laboratory
Author-email: ALGES Lab <contacto@alges.cl>
Project-URL: Repository, https://github.com/alges/spatialize
Keywords: ESI ensemble spatial interpolation
Classifier: Programming Language :: Python :: 3
Classifier: License :: OSI Approved :: MIT License
Classifier: Operating System :: OS Independent
Requires-Python: >=3.8
License-File: LICENSE
Requires-Dist: pandas>=2.2.0
Requires-Dist: numpy
Requires-Dist: jupyter
Requires-Dist: scikit-learn
Requires-Dist: scipy
Requires-Dist: rich
Requires-Dist: tqdm
Requires-Dist: matplotlib
Requires-Dist: opencv-python
Requires-Dist: setuptools
Dynamic: author
Dynamic: home-page
Dynamic: license-file
